pytest_recording/__init__.py
pytest_recording/_vcr.py
pytest_recording/exceptions.py
pytest_recording/hooks.py
pytest_recording/network.py
pytest_recording/plugin.py
pytest_recording/py.typed
pytest_recording/utils.py
pytest_recording/validation.py
pytest_recording-0.13.3.dist-info/METADATA
pytest_recording-0.13.3.dist-info/WHEEL
pytest_recording-0.13.3.dist-info/entry_points.txt
pytest_recording-0.13.3.dist-info/licenses/LICENSE
pytest_recording-0.13.3.dist-info/RECORD
