Metadata-Version: 2.4
Name: pytest-recording
Version: 0.13.3
Summary: A pytest plugin powered by VCR.py to record and replay HTTP traffic
Project-URL: Documentation, https://github.com/kiwicom/pytest-recording
Project-URL: Changelog, https://github.com/kiwicom/pytest-recording/blob/master/docs/changelog.rst
Project-URL: Bug Tracker, https://github.com/kiwicom/pytest-recording/issues
Project-URL: Source Code, https://github.com/kiwicom/pytest-recording
Author-email: Dmitry Dygalo <dmitry@dygalo.dev>
Maintainer-email: Dmitry Dygalo <dmitry@dygalo.dev>
License-Expression: MIT
License-File: LICENSE
Keywords: mock,network,pytest,vcr
Classifier: Development Status :: 4 - Beta
Classifier: Framework :: Pytest
Classifier: Intended Audience :: Developers
Classifier: License :: OSI Approved :: MIT License
Classifier: Operating System :: OS Independent
Classifier: Programming Language :: Python
Classifier: Programming Language :: Python :: 3
Classifier: Programming Language :: Python :: 3 :: Only
Classifier: Programming Language :: Python :: 3.9
Classifier: Programming Language :: Python :: 3.10
Classifier: Programming Language :: Python :: 3.11
Classifier: Programming Language :: Python :: 3.12
Classifier: Programming Language :: Python :: 3.13
Classifier: Programming Language :: Python :: Implementation :: CPython
Classifier: Programming Language :: Python :: Implementation :: PyPy
Classifier: Topic :: Software Development :: Testing
Classifier: Typing :: Typed
Requires-Python: >=3.9
Requires-Dist: pytest>=3.5.0
Requires-Dist: vcrpy>=2.0.1
Provides-Extra: dev
Requires-Dist: pytest-httpbin; extra == 'dev'
Requires-Dist: pytest-mock; extra == 'dev'
Requires-Dist: requests; extra == 'dev'
Requires-Dist: werkzeug==3.1.3; extra == 'dev'
Provides-Extra: tests
Requires-Dist: pytest-httpbin; extra == 'tests'
Requires-Dist: pytest-mock; extra == 'tests'
Requires-Dist: requests; extra == 'tests'
Requires-Dist: werkzeug==3.1.3; extra == 'tests'
